sinabs/backend/dynapcnn/__init__.py
sinabs/backend/dynapcnn/chip_factory.py
sinabs/backend/dynapcnn/config_builder.py
sinabs/backend/dynapcnn/crop2d.py
sinabs/backend/dynapcnn/discretize.py
sinabs/backend/dynapcnn/dvs_layer.py
sinabs/backend/dynapcnn/dynapcnn_layer.py
sinabs/backend/dynapcnn/dynapcnn_network.py
sinabs/backend/dynapcnn/dynapcnn_visualizer.py
sinabs/backend/dynapcnn/exceptions.py
sinabs/backend/dynapcnn/flipdims.py
sinabs/backend/dynapcnn/io.py
sinabs/backend/dynapcnn/mapping.py
sinabs/backend/dynapcnn/specksim.py
sinabs/backend/dynapcnn/utils.py
sinabs/backend/dynapcnn/chips/__init__.py
sinabs/backend/dynapcnn/chips/dynapcnn.py
sinabs/backend/dynapcnn/chips/speck2.py
sinabs/backend/dynapcnn/chips/speck2b.py
sinabs/backend/dynapcnn/chips/speck2cmini.py
sinabs/backend/dynapcnn/chips/speck2dmini.py
sinabs/backend/dynapcnn/chips/speck2e.py
sinabs/backend/dynapcnn/chips/speck2f.py
sinabs_dynapcnn-1.0.15.dist-info/AUTHORS
sinabs_dynapcnn-1.0.15.dist-info/METADATA
sinabs_dynapcnn-1.0.15.dist-info/WHEEL
sinabs_dynapcnn-1.0.15.dist-info/pbr.json
sinabs_dynapcnn-1.0.15.dist-info/top_level.txt
sinabs_dynapcnn-1.0.15.dist-info/RECORD
