Metadata-Version: 2.1
Name: sinabs-dynapcnn
Version: 1.0.15
Summary: sinabs plugin for porting models to chips with DYNAP-CNN technology
Author: SynSense
Author-email: sinabs@synsense.ai
License: GNU AGPLv3
Project-URL: Source Code, https://gitlab.com/synsense/sinabs-dynapcnn
Project-URL: Documentation, https://synsense.gitlab.io/sinabs-dynapcnn
Keywords: spiking,SNN,DYNAPCNN,Speck
Classifier: Development Status :: 4 - Beta
Classifier: Environment :: Console
Classifier: Intended Audience :: Science/Research
Classifier: Intended Audience :: Developers
Classifier: License :: OSI Approved :: GNU Affero General Public License v3 or later (AGPLv3+)
Classifier: Programming Language :: Python :: 3
License-File: AUTHORS
Requires-Dist: pbr
Requires-Dist: sinabs (>=1.1.6)
Requires-Dist: samna (>=0.33)
